bmonreporter/__init__.py
bmonreporter/config_logging.py
bmonreporter/file_util.py
bmonreporter/reporter.py
bmonreporter-1.0.2.data/scripts/bmonreporter
bmonreporter-1.0.2.dist-info/LICENSE
bmonreporter-1.0.2.dist-info/METADATA
bmonreporter-1.0.2.dist-info/WHEEL
bmonreporter-1.0.2.dist-info/top_level.txt
bmonreporter-1.0.2.dist-info/RECORD
