Metadata-Version: 2.1
Name: bmonreporter
Version: 1.0.2
Summary: Creates Energy Reports from BMON Servers.
Home-page: https://github.com/alanmitchell/bmonreporter
Author: Alan Mitchell
Author-email: tabb99@gmail.com
License: UNKNOWN
Platform: UNKNOWN
Classifier: Programming Language :: Python :: 3
Classifier: License :: OSI Approved :: Apache Software License
Classifier: Operating System :: OS Independent
Requires-Python: >=3.6
Requires-Dist: pyyaml (>=5.1.1)
Requires-Dist: awscli (>=1.16.264)
Requires-Dist: papermill (<3)
Requires-Dist: scrapbook (<1)
Requires-Dist: jupyterthemes (>=0.20.0)
